[
  {
    "id": "bd0f6fac-624c-4ed6-8bcd-4ea76a196f9e",
    "name": {
      "firstname": "Gaëlle",
      "lastname": "ARNAUD"
    },
    "address": {
      "street": "598 Boulevard Charlemagne",
      "city": "Issy-les-Moulineaux",
      "zipcode": "08246"
    }
  },
  {
    "id": "e38e9a1a-e885-4865-9e02-30eddc4fe7ff",
    "name": {
      "firstname": "Justin",
      "lastname": "DUBOIS"
    },
    "address": {
      "street": "7832 Rue Saint-Honoré",
      "city": "Noisy-le-Grand",
      "zipcode": "66924"
    }
  },
  {
    "id": "1656a4e9-9c92-48c4-a4c1-e9ac33f1426d",
    "name": {
      "firstname": "Matthieu",
      "lastname": "MARTINEZ"
    },
    "address": {
      "street": "78 Impasse Zadkine",
      "city": "Cayenne",
      "zipcode": "57696"
    }
  },
  {
    "id": "5cb4c148-30ea-4fa3-96c0-c51d7f2a63cd",
    "name": {
      "firstname": "Alverède",
      "lastname": "LAMBERT"
    },
    "address": {
      "street": "91 Quai Montorgueil",
      "city": "Nîmes",
      "zipcode": "72088"
    }
  },
  {
    "id": "30fbc1df-9b99-40db-b4a3-2ce30934a87c",
    "name": {
      "firstname": "Manon",
      "lastname": "MOREL"
    },
    "address": {
      "street": "928 Boulevard de Vaugirard",
      "city": "Ajaccio",
      "zipcode": "85108"
    }
  },
  {
    "id": "b80337bb-c69d-4abd-89ea-e0c913f4ff39",
    "name": {
      "firstname": "Joanny",
      "lastname": "SCHMITT"
    },
    "address": {
      "street": "3266 Avenue de la Pompe",
      "city": "Montreuil",
      "zipcode": "78472"
    }
  },
  {
    "id": "11775e0e-53a1-477f-ae60-5eb2d2300bf6",
    "name": {
      "firstname": "Jeanne d’Arc",
      "lastname": "ROLLAND"
    },
    "address": {
      "street": "5 Rue de Richelieu",
      "city": "Limoges",
      "zipcode": "41264"
    }
  },
  {
    "id": "80c8c36a-426f-499e-ae61-b3c496b56ff6",
    "name": {
      "firstname": "Agnane",
      "lastname": "MARTINEZ"
    },
    "address": {
      "street": "61 Voie d'Abbeville",
      "city": "Reims",
      "zipcode": "64020"
    }
  },
  {
    "id": "a8443729-4cdf-4073-a915-7d9ca1406fa3",
    "name": {
      "firstname": "Fabien",
      "lastname": "LECLERC"
    },
    "address": {
      "street": "9 Quai d'Argenteuil",
      "city": "Toulon",
      "zipcode": "93336"
    }
  },
  {
    "id": "cc3f21bb-d366-43f2-812e-0394ee77cee2",
    "name": {
      "firstname": "Savin",
      "lastname": "CARPENTIER"
    },
    "address": {
      "street": "38 Voie Dauphine",
      "city": "Mérignac",
      "zipcode": "46883"
    }
  },
  {
    "id": "4344ba48-d082-46e2-8ca7-2602b646468a",
    "name": {
      "firstname": "Béranger",
      "lastname": "PETIT"
    },
    "address": {
      "street": "917 Rue de la Chaussée-d'Antin",
      "city": "Nancy",
      "zipcode": "69636"
    }
  },
  {
    "id": "fce92237-12c6-46d3-8c52-32c154911514",
    "name": {
      "firstname": "Aurèle",
      "lastname": "MARIE"
    },
    "address": {
      "street": "27 Impasse de Caumartin",
      "city": "Ajaccio",
      "zipcode": "40151"
    }
  },
  {
    "id": "56a323ba-7169-48f5-b901-c44e1e00e697",
    "name": {
      "firstname": "Alphée",
      "lastname": "ROLLAND"
    },
    "address": {
      "street": "23 Place de la Chaussée-d'Antin",
      "city": "Poitiers",
      "zipcode": "03074"
    }
  },
  {
    "id": "99a7d158-4504-4fac-afd2-284bd9bb6d32",
    "name": {
      "firstname": "Blandine",
      "lastname": "BRUNET"
    },
    "address": {
      "street": "69 Avenue des Francs-Bourgeois",
      "city": "Versailles",
      "zipcode": "97387"
    }
  },
  {
    "id": "04b2c27d-75fc-4e8b-8061-9ff2afed92a4",
    "name": {
      "firstname": "Bernadette",
      "lastname": "GAILLARD"
    },
    "address": {
      "street": "59 Passage de Richelieu",
      "city": "Noisy-le-Grand",
      "zipcode": "79681"
    }
  }
]
